Workbook

Sheet  INGRESOS
A1: INGRESOS
A3: FECHA INGRESO | B3: · FACTURA Nª | C3: TIPO DE INGRESO | D3: DOCUMENTO | E3: NOMBRE | F3: DIRECCION | G3: CORREO | H3: TELEFONO | I3: INGRESO COP

Sheet GASTOS
A1: GASTOS
F2: =SUM(F4:F150) -> 0
A3: FECHA | B3: DOCUMENTO | C3: PROVEEDOR | D3: CATEGORIA | E3: METODO DE PAGO | F3: GASTO TOTAL COP | G3: NOTAS

Sheet INFORME MES 
A1: INFORME FINANCIERO
A6: RESULTADO
B12: =F59-C23 -> 0 | H12: =O59-J33 -> 0
B13: INGRESOS | H13: GASTOS | M13: =Z60
B14: TIPO DE INGRESO | C14: INGRESO COP | D14: % | H14: CATEGORIAS | I14: % | J14: VALOR
B15: CARTERA | C15: =SUMIF(C40:C70,B15,F40:F70) -> 543000000 | D15: =C15/$C$23 -> 0.8858075 | H15: Comisiones | I15: =J15/$J$33 -> 0.13907285 | J15: =SUMIF($M$40:M70,H15,$O$40:O70) -> 21000000
B16: VENTA | C16: =SUMIF(C41:C71,B16,F41:F71) -> 30000000 | D16: =C16/$C$23 -> 0.048939641 | H16: Herramientas | I16: =J16/$J$33 -> 0.099337748 | J16: =SUMIF($M$40:M71,H16,$O$40:O71) -> 15000000
B17: OTRO | C17: =SUMIF(C42:C72,B17,F42:F72) -> 40000000 | D17: =C17/$C$23 -> 0.065252855 | H17: Impuestos | I17: =J17/$J$33 -> 0.1192053 | J17: =SUMIF($M$40:M72,H17,$O$40:O72) -> 18000000
C18: =SUMIF(C43:C73,B18,F43:F73) -> 0 | H18: Nómina | I18: =J18/$J$33 -> 0.13245033 | J18: =SUMIF($M$40:M73,H18,$O$40:O73) -> 20000000
C19: =SUMIF(C44:C74,B19,F44:F74) -> 0 | H19: Otros | I19: =J19/$J$33 -> 0.12582781 | J19: =SUMIF($M$40:M74,H19,$O$40:O74) -> 19000000
C20: =SUMIF(C45:C75,B20,F45:F75) -> 0 | H20: Proveedores | I20: =J20/$J$33 -> 0.072847682 | J20: =SUMIF($M$40:M75,H20,$O$40:O75) -> 11000000
C21: =SUMIF(C46:C76,B21,F46:F76) -> 0 | H21: Publicidad | I21: =J21/$J$33 -> 0.066225166 | J21: =SUMIF($M$40:M76,H21,$O$40:O76) -> 10000000
C22: =SUMIF(C47:C77,B22,F47:F77) -> 0 | H22: Viajes | I22: =J22/$J$33 -> 0.099337748 | J22: =SUMIF($M$40:M77,H22,$O$40:O77) -> 15000000
C23: =SUM(C15:C22) -> 613000000 | H23: Mentores | I23: =J23/$J$33 -> 0.099337748 | J23: =SUMIF($M$40:M78,H23,$O$40:O78) -> 15000000
H24: Educacion | I24: =J24/$J$33 -> 0.046357616 | J24: =SUMIF($M$40:M79,H24,$O$40:O79) -> 7000000
I25: =J25/J43 -> 0 | J25: =SUMIF($M$40:M80,H25,$O$40:O80) -> 0
I26: =J26/J44 -> 0
I27: =J27/J45 -> 0
I28: =J28/J46 -> 0
I29: =J29/J47 -> 0
I30: =J30/J48 -> 0
I31: =J31/J49 -> 0
H33: TOTAL | I33: =SUM(I15:I32) -> 1 | J33: =SUM(J15:J32) -> 151000000
A39: FECHA INGRESO | B39: N FAC | C39: TIPO DE INGRESO | D39: NOMBRE | F39: INGRESO COP | G39: Docuemtno soporte | J39: FECHA | K39: DOCUMENTO | L39: PROVEEDOR | M39: CATEGORIA | N39: METODO DE PAGO | O39: GASTO

Sheet ANUAL
A1: INFORME FINANCIERO
C9: INGRESOS
C10: TIPO DE INGRESO | D10: ENERO | E10: FEBRERO | F10: MARZO | G10: ABRIL | H10: MAYO
C11: CARTERA | D11: ='INFORME MES '!C15 -> 543000000
C12: VENTA | D12: ='INFORME MES '!C16 -> 30000000
C13: OTRO | D13: ='INFORME MES '!C17 -> 40000000
D14: ='INFORME MES '!C18 -> 0
D15: ='INFORME MES '!C19 -> 0
D16: ='INFORME MES '!C20 -> 0
D17: ='INFORME MES '!C21 -> 0
D18: ='INFORME MES '!C22 -> 0
D19: =SUM(D11:D18) -> 613000000
C27: GASTOS 2026
C28: CATEGORIAS | D28: ENERO | E28: FEBRERO | F28: MARZO | G28: ABRIL | H28: MAYO
C29: Comisiones | D29: ='INFORME MES '!J15 -> 21000000
C30: Herramientas | D30: ='INFORME MES '!J16 -> 15000000
C31: Impuestos | D31: ='INFORME MES '!J17 -> 18000000
C32: Nómina | D32: ='INFORME MES '!J18 -> 20000000
C33: Otros | D33: ='INFORME MES '!J19 -> 19000000
C34: Proveedores | D34: ='INFORME MES '!J20 -> 11000000
C35: Publicidad | D35: ='INFORME MES '!J21 -> 10000000
C36: Viajes | D36: ='INFORME MES '!J22 -> 15000000
C37: Mentores | D37: ='INFORME MES '!J23 -> 15000000
C38: Educacion | D38: ='INFORME MES '!J24 -> 7000000
D44: =SUM(D29:D43) -> 151000000 | E44: =SUM(E29:E43) -> 0 | F44: =SUM(F29:F43) -> 0 | G44: =SUM(G29:G43) -> 0 | H44: =SUM(H29:H43) -> 0 | I44: =SUM(I29:I43) -> 0
